CHANGES.rst
MANIFEST.in
README.rst
requirements.txt
setup.py
consumer/__init__.py
consumer/consumers.py
consumer/exceptions.py
consumer/handlers.py
consumer/main.py
consumer/utils.py
consumer/configs/__init__.py
consumer/configs/default.py
consumer/tests/__init__.py
consumer/tests/sample_config/default.yml
sc_gitlab_msg_consumer.egg-info/PKG-INFO
sc_gitlab_msg_consumer.egg-info/SOURCES.txt
sc_gitlab_msg_consumer.egg-info/dependency_links.txt
sc_gitlab_msg_consumer.egg-info/entry_points.txt
sc_gitlab_msg_consumer.egg-info/requires.txt
sc_gitlab_msg_consumer.egg-info/top_level.txt