Metadata-Version: 1.2
Name: sc-gitlab-msg-consumer
Version: 0.0.2
Summary: A rocketmq message consumer for Gitlab WebHook messages
Home-page: https://github.com/Scott-Lau/sc-msg-consumer
Author: Scott Lau
Author-email: exceedego@126.com
License: MIT
Keywords: Git Gitlab Python WebHook Consumer
Platform: POSIX
Classifier: Programming Language :: Python :: 3
Classifier: Programming Language :: Python :: 3.6
Classifier: Programming Language :: Python :: 3.7
Classifier: Programming Language :: Python :: 3.8
Classifier: Programming Language :: Python :: 3.9
Classifier: License :: OSI Approved :: MIT License
Classifier: Operating System :: OS Independent
Classifier: Topic :: Software Development
Classifier: Topic :: Utilities
Requires-Python: >=3.6
